facebook_sdk/__init__.py
facebook_sdk/authentication.py
facebook_sdk/client.py
facebook_sdk/constants.py
facebook_sdk/exceptions.py
facebook_sdk/facebook.py
facebook_sdk/file_upload.py
facebook_sdk/request.py
facebook_sdk/response.py
facebook_sdk/utils.py
facebook_sdk_python-0.0.4.dist-info/DESCRIPTION.rst
facebook_sdk_python-0.0.4.dist-info/METADATA
facebook_sdk_python-0.0.4.dist-info/RECORD
facebook_sdk_python-0.0.4.dist-info/WHEEL
facebook_sdk_python-0.0.4.dist-info/metadata.json
facebook_sdk_python-0.0.4.dist-info/top_level.txt
