Metadata-Version: 2.0
Name: facebook-sdk-python
Version: 0.0.4
Summary: Facebook Python SDK
Home-page: http://github.com/zetahernandez/facebook-python-sdk
Author: Zeta Hernandez
Author-email: zetahernandez@gmail.com
License: MIT
Platform: UNKNOWN
Classifier: License :: OSI Approved :: MIT License
Classifier: Programming Language :: Python
Classifier: Programming Language :: Python :: 2.6
Classifier: Programming Language :: Python :: 2.7
Classifier: Programming Language :: Python :: 3.3
Classifier: Programming Language :: Python :: 3.4
Classifier: Programming Language :: Python :: 3.5
Requires-Dist: requests (>=0.8)
Requires-Dist: six (>=1.6)
